CryptoAesGcm/CryptoAesGcm.py
CryptoAesGcm/__init__.py
CryptoAesGcm-0.0.7.dist-info/METADATA
CryptoAesGcm-0.0.7.dist-info/WHEEL
CryptoAesGcm-0.0.7.dist-info/top_level.txt
CryptoAesGcm-0.0.7.dist-info/RECORD
