Metadata-Version: 2.1
Name: CryptoAesGcm
Version: 0.0.7
Summary: Wrapper for Crypto library to get encrytped key and data using less code and less complexity.
Home-page: https://github.com/sethhardik/CryptoAesGcm
Author: Hardik Seth
Author-email: <hseth469@gmail.com>
License: UNKNOWN
Keywords: python,Encryption,Decryption,Cypher,Aes,GCM
Platform: UNKNOWN
Classifier: Development Status :: 4 - Beta
Classifier: Intended Audience :: Developers
Classifier: Programming Language :: Python :: 3
Classifier: Operating System :: Unix
Classifier: Operating System :: MacOS :: MacOS X
Classifier: Operating System :: Microsoft :: Windows
Classifier: License :: OSI Approved :: MIT License
Requires-Dist: pycrypto
